odoo/addons/sale_blanket_order_comment/LICENSE
odoo/addons/sale_blanket_order_comment/README.rst
odoo/addons/sale_blanket_order_comment/__init__.py
odoo/addons/sale_blanket_order_comment/__manifest__.py
odoo/addons/sale_blanket_order_comment/i18n/de.po
odoo/addons/sale_blanket_order_comment/images/screen.png
odoo/addons/sale_blanket_order_comment/models/__init__.py
odoo/addons/sale_blanket_order_comment/models/blanket_order.py
odoo/addons/sale_blanket_order_comment/static/description/icon.png
odoo/addons/sale_blanket_order_comment/static/description/index.html
odoo/addons/sale_blanket_order_comment/tests/TEST_INSTRUCTIONS.rst
odoo/addons/sale_blanket_order_comment/views/sale_blanket_order.xml
odoo/addons/sale_blanket_order_comment/wizard/__init__.py
odoo/addons/sale_blanket_order_comment/wizard/create_sale_orders.py
odoo_addon_sale_blanket_order_comment-16.0.1.0.0.dist-info/METADATA
odoo_addon_sale_blanket_order_comment-16.0.1.0.0.dist-info/WHEEL
odoo_addon_sale_blanket_order_comment-16.0.1.0.0.dist-info/top_level.txt
odoo_addon_sale_blanket_order_comment-16.0.1.0.0.dist-info/RECORD
